[{"nome": "CJ | INTERESSES | REGIONAL | HAVAL H6", "reg": "", "can": "Form", "dailyLiq": 436.3, "status": "ACTIVE"}, {"nome": "CJ | ABERTO | REGIONAL | TANK", "reg": "", "can": "Form", "dailyLiq": 201.32, "status": "ACTIVE"}, {"nome": "CJ | ABERTO | ELD | H6", "reg": "", "can": "WhatsApp", "dailyLiq": 130.4, "status": "ACTIVE"}, {"nome": "CJ | ABERTO | ALP | H6", "reg": "", "can": "WhatsApp", "dailyLiq": 130.4, "status": "ACTIVE"}, {"nome": "CJ | ABERTO | EUR | H6", "reg": "", "can": "WhatsApp", "dailyLiq": 130.4, "status": "ACTIVE"}, {"nome": "CJ | ABERTO | FMO | H6", "reg": "", "can": "WhatsApp", "dailyLiq": 130.4, "status": "ACTIVE"}, {"nome": "CJ | ABERTO | VLO | H6", "reg": "", "can": "WhatsApp", "dailyLiq": 121.31, "status": "ACTIVE"}, {"nome": "CJ | ABERTO | REGIONAL | ORA", "reg": "", "can": "Form", "dailyLiq": 101.46, "status": "ACTIVE"}, {"nome": "CJ | ABERTO | REGIONAL | H9", "reg": "", "can": "Form", "dailyLiq": 101.46, "status": "ACTIVE"}, {"nome": "CJ | ABERTO | REGIONAL | WEY", "reg": "", "can": "Form", "dailyLiq": 60.88, "status": "ACTIVE"}, {"nome": "CJ | ABERTO | REGIONAL | POER", "reg": "", "can": "Form", "dailyLiq": 60.88, "status": "ACTIVE"}, {"nome": "CJ | ABERTO | VLO | TANK", "reg": "", "can": "WhatsApp", "dailyLiq": 60.65, "status": "ACTIVE"}, {"nome": "CJ | ABERTO | ELD | TANK", "reg": "", "can": "WhatsApp", "dailyLiq": 60.65, "status": "ACTIVE"}, {"nome": "CJ | ABERTO | ALP | TANK", "reg": "", "can": "WhatsApp", "dailyLiq": 60.65, "status": "ACTIVE"}, {"nome": "CJ | ABERTO | EUR | TANK", "reg": "", "can": "WhatsApp", "dailyLiq": 60.65, "status": "ACTIVE"}, {"nome": "CJ | ABERTO | FMO | TANK", "reg": "", "can": "WhatsApp", "dailyLiq": 60.65, "status": "ACTIVE"}, {"nome": "CJ | INTERESSES | ALP | PV", "reg": "", "can": "WhatsApp", "dailyLiq": 47.95, "status": "ACTIVE"}, {"nome": "CJ | INTERESSES | FMO | PV", "reg": "", "can": "WhatsApp", "dailyLiq": 47.95, "status": "ACTIVE"}, {"nome": "CJ | INTERESSES | VLO | PV", "reg": "", "can": "WhatsApp", "dailyLiq": 47.95, "status": "ACTIVE"}, {"nome": "CJ | ABERTO | FMO | H9", "reg": "", "can": "WhatsApp", "dailyLiq": 40.5, "status": "ACTIVE"}, {"nome": "CJ | ABERTO | VLO | H9", "reg": "", "can": "WhatsApp", "dailyLiq": 39.42, "status": "ACTIVE"}, {"nome": "CJ | ABERTO | EUR | H9", "reg": "", "can": "WhatsApp", "dailyLiq": 39.42, "status": "ACTIVE"}, {"nome": "🟩 DSPA | GWM | NV | FORM | SP || JOAO BRIGATO", "reg": "", "can": "Form", "dailyLiq": 32.26, "status": "ACTIVE"}, {"nome": "CJ | ABERTO | VLO |  ORA", "reg": "", "can": "WhatsApp", "dailyLiq": 30.33, "status": "ACTIVE"}, {"nome": "CJ | ABERTO | ELD | ORA", "reg": "", "can": "WhatsApp", "dailyLiq": 30.33, "status": "ACTIVE"}, {"nome": "CJ | ABERTO | ELD | H9", "reg": "", "can": "WhatsApp", "dailyLiq": 30.33, "status": "ACTIVE"}, {"nome": "CJ | ABERTO | ALP | H9", "reg": "", "can": "WhatsApp", "dailyLiq": 30.33, "status": "ACTIVE"}, {"nome": "CJ | ABERTO | ALP | ORA", "reg": "", "can": "WhatsApp", "dailyLiq": 30.33, "status": "ACTIVE"}, {"nome": "CJ | ABERTO | EUR | ORA", "reg": "", "can": "WhatsApp", "dailyLiq": 30.33, "status": "ACTIVE"}, {"nome": "CJ | ABERTO | FMO | ORA", "reg": "", "can": "WhatsApp", "dailyLiq": 30.33, "status": "ACTIVE"}, {"nome": "CJ | INTERESSES | ELD | VD", "reg": "", "can": "WhatsApp", "dailyLiq": 23.59, "status": "ACTIVE"}, {"nome": "CJ | INTERESSES | EUR | VD", "reg": "", "can": "WhatsApp", "dailyLiq": 23.59, "status": "ACTIVE"}, {"nome": "CJ | INTERESSES | VLO | VD", "reg": "", "can": "WhatsApp", "dailyLiq": 23.59, "status": "ACTIVE"}, {"nome": "CJ | INTERESSES | ALP | VD", "reg": "", "can": "WhatsApp", "dailyLiq": 23.59, "status": "ACTIVE"}, {"nome": "CJ | INTERESSES | FMO | VD", "reg": "", "can": "WhatsApp", "dailyLiq": 23.59, "status": "ACTIVE"}, {"nome": "CJ | ABERTO | VLO | POER", "reg": "", "can": "WhatsApp", "dailyLiq": 21.81, "status": "ACTIVE"}, {"nome": "CJ | ABERTO | EUR | POER", "reg": "", "can": "WhatsApp", "dailyLiq": 21.81, "status": "ACTIVE"}, {"nome": "CJ | ABERTO | EUR | WEY", "reg": "", "can": "WhatsApp", "dailyLiq": 21.81, "status": "ACTIVE"}, {"nome": "CJ | ABERTO | FMO | POER", "reg": "", "can": "WhatsApp", "dailyLiq": 21.81, "status": "ACTIVE"}, {"nome": "CJ | ABERTO | FMO | WEY", "reg": "", "can": "WhatsApp", "dailyLiq": 21.81, "status": "ACTIVE"}, {"nome": "CJ | ABERTO | VLO | WEY", "reg": "", "can": "WhatsApp", "dailyLiq": 21.23, "status": "ACTIVE"}, {"nome": "CJ | ABERTO | ELD | WEY", "reg": "", "can": "WhatsApp", "dailyLiq": 21.23, "status": "ACTIVE"}, {"nome": "CJ | ABERTO | ALP | POER", "reg": "", "can": "WhatsApp", "dailyLiq": 18.69, "status": "ACTIVE"}, {"nome": "CJ | ABERTO | ELD | POER", "reg": "", "can": "WhatsApp", "dailyLiq": 18.2, "status": "ACTIVE"}, {"nome": "CJ | ABERTO | ALP | WEY", "reg": "", "can": "WhatsApp", "dailyLiq": 18.2, "status": "ACTIVE"}, {"nome": "CJ | ABERTO | 0 | LANCAMENTO_ORA5", "reg": "", "can": "Engaj", "dailyLiq": 16.57, "status": "ACTIVE"}, {"nome": "CJ | ABERTO | REGIONAL |", "reg": "", "can": "Engaj", "dailyLiq": 16.57, "status": "ACTIVE"}, {"nome": "CJ_ELD_SP-AMPLO_MODELOS", "reg": "", "can": "WhatsApp", "dailyLiq": 12.13, "status": "ACTIVE"}]